{
  "polinizacao": {
    "url": "https://news.google.com/news/rss/search?q=kiwifruit%20pollination&hl=en",
    "descricao": "Notícias recentes sobre polinização de kiwis"
  },
  "zespri": {
    "url": "https://rss.app/feeds/waxKIY1WgCjtxLEs.xml",
    "descricao": "Atualizações do Kiwiflier da Zespri"
  },
  "apkiwi": {
    "url": "https://morss.it/:clip:items=%7C%7C*%5Bclass=fs-1%5D/https://www.comunicamaiskiwi.apk.com.pt/artigos",
    "descricao": "Novos artigos dos APKiwicultores"
  },
  "canopy": {
    "url": "https://www.google.com/alerts/feeds/15846699374716510861/18443315587638399243",
    "descricao": "Novos documentos publicados no Zespri Canopy"
  },
  "bioseguranca": {
    "url": "https://www.google.com/alerts/feeds/15846699374716510861/15614409539590136616",
    "descricao": "Novidades da Kiwi Vine Health sobre biosegurança do kiwi"
  },
  "kiwiko": {
    "url": "https://rss.app/feeds/sFMbornI2qY1K91A.xml",
    "descricao": "Novos posts da Kiwiko sobre desenvolvimento de variedades de kiwi"
  }
}
